[
  {
    "reference": "https://www.eclipse.org/org/documents/edl-v10.html",
    "isDeprecatedLicenseId": false,
    "detailsUrl": "https://www.eclipse.org/org/documents/edl-v10.php",
    "referenceNumber": 999,
    "name": "Eclipse Distribution License 1.0",
    "licenseId": "EDL-1.0",
    "isSpdxListed": false,
    "isOsiApproved": true,
    "isFsfLibre": true,
    "isCncfApproved": true,
    "licenseReference": "BSD-3-Clause"
  },
  {
    "reference": "https://www.bouncycastle.org/about/license/",
    "isDeprecatedLicenseId": false,
    "detailsUrl": "https://www.bouncycastle.org/about/license/",
    "referenceNumber": 999,
    "name": "Bouncy Castle Licence",
    "licenseId": "BouncyCastle",
    "isSpdxListed": false,
    "isOsiApproved": true,
    "isFsfLibre": true,
    "isCncfApproved": true,
    "licenseReference": "MIT"
  },
  {
    "reference": "https://www.oracle.com/downloads/licenses/oracle-free-license.html",
    "isDeprecatedLicenseId": false,
    "detailsUrl": "https://www.oracle.com/downloads/licenses/oracle-free-license.html",
    "referenceNumber": 999,
    "name": "Oracle Free Use Terms and Conditions (FUTC)",
    "licenseId": "OracleFUTC",
    "isSpdxListed": false,
    "isOsiApproved": false,
    "isFsfLibre": false,
    "isCncfApproved": false
  }
]